autonet/__init__.py
autonet/__version__.py
autonet/config.py
autonet/conftest.py
autonet/blueprints/__init__.py
autonet/blueprints/bridge_vlan.py
autonet/blueprints/interface.py
autonet/blueprints/interface_lag.py
autonet/blueprints/options.py
autonet/blueprints/tunnels_vxlan.py
autonet/blueprints/users.py
autonet/blueprints/vrf.py
autonet/commands/__init__.py
autonet/commands/createadmin.py
autonet/core/__init__.py
autonet/core/app.py
autonet/core/device.py
autonet/core/exceptions.py
autonet/core/logging.py
autonet/core/marshal.py
autonet/core/response.py
autonet/core/objects/__init__.py
autonet/core/objects/interfaces.py
autonet/core/objects/lag.py
autonet/core/objects/validators.py
autonet/core/objects/vlan.py
autonet/core/objects/vrf.py
autonet/core/objects/vxlan.py
autonet/core/tests/__init__.py
autonet/core/tests/conftest.py
autonet/core/tests/test_app.py
autonet/core/tests/test_device.py
autonet/core/tests/test_marshal.py
autonet/core/tests/test_response.py
autonet/db/__init__.py
autonet/db/base.py
autonet/db/mixins.py
autonet/db/models.py
autonet/db/types.py
autonet/drivers/__init__.py
autonet/drivers/backend/__init__.py
autonet/drivers/backend/base.py
autonet/drivers/backend/deviceconf/__init__.py
autonet/drivers/backend/deviceconf/deviceconf.py
autonet/drivers/backend/netbox/__init__.py
autonet/drivers/backend/netbox/netbox.py
autonet/drivers/backend/yamlfile/__init__.py
autonet/drivers/backend/yamlfile/yamlfile.py
autonet/drivers/device/__init__.py
autonet/drivers/device/driver.py
autonet/drivers/device/dummy_driver/__init__.py
autonet/drivers/device/dummy_driver/driver.py
autonet/util/__init__.py
autonet/util/auth.py
autonet/util/config_string.py
autonet/util/evpn.py
autonet_api-0.2.1.dist-info/LICENSE.txt
autonet_api-0.2.1.dist-info/METADATA
autonet_api-0.2.1.dist-info/WHEEL
autonet_api-0.2.1.dist-info/entry_points.txt
autonet_api-0.2.1.dist-info/top_level.txt
autonet_api-0.2.1.dist-info/RECORD
